apteryx_transformers/GLOBALS.py
apteryx_transformers/__init__.py
apteryx_transformers/apteryx_datasets.py
apteryx_transformers/collators.py
apteryx_transformers/models/__init__.py
apteryx_transformers/models/autoencoders.py
apteryx_transformers/models/classifiers.py
apteryx_transformers/models/t5variants.py
apteryx_transformers/parsers/__init__.py
apteryx_transformers/parsers/noun_phrase_parser.py
apteryx_transformers/parsers/parser_utils.py
apteryx_transformers/simulated_annealing/__init__.py
apteryx_transformers/simulated_annealing/annealers.py
apteryx_transformers/simulated_annealing/heuristics/__init__.py
apteryx_transformers/simulated_annealing/heuristics/fluency.py
apteryx_transformers/simulated_annealing/heuristics/length.py
apteryx_transformers/simulated_annealing/heuristics/semantics.py
apteryx_transformers/simulated_annealing/proposers.py
apteryx_transformers/tc_count
apteryx_transformers/utils/__init__.py
apteryx_transformers/utils/loading.py
apteryx_transformers/utils/saliency_interpreter.py
apteryx_transformers/utils/smooth_gradient.py
apteryx_transformers/utils/visualization.py
apteryx_transformers-0.1.5.dist-info/WHEEL
apteryx_transformers-0.1.5.dist-info/METADATA
apteryx_transformers-0.1.5.dist-info/RECORD
